oss/__init__.py
oss/api.py
oss/auth.py
oss/compat.py
oss/crc64_combine.py
oss/defaults.py
oss/entity.py
oss/exceptions.py
oss/headers.py
oss/http.py
oss/select_params.py
oss/select_response.py
oss/utils.py
oss/xml_utils.py
python_oss_sdk-1.0.0.dist-info/METADATA
python_oss_sdk-1.0.0.dist-info/WHEEL
python_oss_sdk-1.0.0.dist-info/top_level.txt
python_oss_sdk-1.0.0.dist-info/RECORD
